systematic/__init__.py
systematic/classes.py
systematic/dates.py
systematic/dmi.py
systematic/log.py
systematic/process.py
systematic/rsync.py
systematic/serverlist.py
systematic/services.py
systematic/shell.py
systematic/smart.py
systematic/sqlite.py
systematic/sshconfig.py
systematic/startup.py
systematic/tail.py
systematic/user.py
systematic/filesystems/__init__.py
systematic/filesystems/zfs/__init__.py
systematic/filesystems/zfs/zfs.py
systematic/filesystems/zfs/zpool.py
systematic/logformats/__init__.py
systematic/logformats/nagios.py
systematic/platform/__init__.py
systematic/platform/system.py
systematic/platform/bsd/__init__.py
systematic/platform/bsd/filesystems.py
systematic/platform/bsd/iostat.py
systematic/platform/bsd/stats.py
systematic/platform/bsd/system.py
systematic/platform/darwin/__init__.py
systematic/platform/darwin/diskutil.py
systematic/platform/darwin/filesystems.py
systematic/platform/darwin/iostat.py
systematic/platform/darwin/stats.py
systematic/platform/darwin/system.py
systematic/platform/linux/__init__.py
systematic/platform/linux/filesystems.py
systematic/platform/linux/iostat.py
systematic/platform/linux/stats.py
systematic/platform/linux/system.py
systematic/stats/__init__.py
systematic/stats/filesystems/__init__.py
systematic/stats/filesystems/zfs.py
systematic/stats/hardware/__init__.py
systematic/stats/hardware/dmi.py
systematic/stats/hardware/pciconf.py
systematic/stats/hardware/smart.py
systematic/stats/network/__init__.py
systematic/stats/network/lsof.py
systematic/stats/services/__init__.py
systematic/stats/services/nginx.py
systematic/stats/system/__init__.py
systematic-4.8.7.data/scripts/servers
systematic-4.8.7.data/scripts/smart-status
systematic-4.8.7.data/scripts/ssh-config
systematic-4.8.7.data/scripts/xml-reformat
test/__init__.py
test/conftest.py
test/test_dates.py
test/test_process.py
test/test_sqlite.py
test/filesystems/__init__.py
test/filesystems/test_mountpoints.py
test/filesystems/test_zfs.py
systematic-4.8.7.dist-info/METADATA
systematic-4.8.7.dist-info/WHEEL
systematic-4.8.7.dist-info/top_level.txt
systematic-4.8.7.dist-info/RECORD
