Metadata-Version: 1.1
Name: systematic
Version: 4.8.7
Summary: Sysadmin utility classes and scripts
Home-page: https://github.com/hile/systematic/
Author: Ilkka Tuohela
Author-email: hile@iki.fi
License: PSF
Keywords: system management utility scripts
Platform: UNKNOWN
Classifier: Environment :: Console
Classifier: Intended Audience :: Developers
Classifier: Intended Audience :: System Administrators
Classifier: License :: OSI Approved :: Python Software Foundation License
Classifier: Operating System :: POSIX
Classifier: Operating System :: MacOS :: MacOS X
Classifier: Programming Language :: Python :: 2.7
Classifier: Programming Language :: Python :: 3
Classifier: Topic :: System
Classifier: Topic :: System :: Systems Administration
